Metadata-Version: 1.0
Name: whmcs-restapi
Version: 0.0.1
Summary: Rest API server for WHMCS SOAP like HTTP API
Home-page: UNKNOWN
Author: Zekeriya Koc
Author-email: zekzekus@gmail.com
License: Gnu General Public License v3
Keywords: rest server api flask whmcs http
Platform: UNKNOWN
